{
    "dialogue_id": "A01805",
    "dialogue_type": "First time",
    "interlocutors": [
        "はくさい",
        "あずき",
        "きなこ"
    ],
    "relationship": [],
    "utterances": [
        {
            "utterance_id": 0,
            "interlocutor_id": "はくさい",
            "text": "おはようございます",
            "mention_to": []
        },
        {
            "utterance_id": 1,
            "interlocutor_id": "あずき",
            "text": "おはようございます",
            "mention_to": []
        },
        {
            "utterance_id": 2,
            "interlocutor_id": "きなこ",
            "text": "おはようございます",
            "mention_to": []
        },
        {
            "utterance_id": 3,
            "interlocutor_id": "はくさい",
            "text": "子ども連れで旅行ってどんなところいいですかね？",
            "mention_to": []
        },
        {
            "utterance_id": 4,
            "interlocutor_id": "きなこ",
            "text": "@はくさい 何歳くらいですか？",
            "mention_to": [
                "はくさい"
            ]
        },
        {
            "utterance_id": 5,
            "interlocutor_id": "あずき",
            "text": "@はくさい 動物園とかですかねー",
            "mention_to": [
                "はくさい"
            ]
        },
        {
            "utterance_id": 6,
            "interlocutor_id": "あずき",
            "text": "子供の楽しめるスポット",
            "mention_to": []
        },
        {
            "utterance_id": 7,
            "interlocutor_id": "あずき",
            "text": "巡ります",
            "mention_to": []
        },
        {
            "utterance_id": 8,
            "interlocutor_id": "あずき",
            "text": "ディズニーとか？",
            "mention_to": []
        },
        {
            "utterance_id": 9,
            "interlocutor_id": "はくさい",
            "text": "@きなこ この4月から小1小４中１です",
            "mention_to": [
                "きなこ"
            ]
        },
        {
            "utterance_id": 10,
            "interlocutor_id": "きなこ",
            "text": "@あずき 動物園いいですね、ディズニーも！",
            "mention_to": [
                "あずき"
            ]
        },
        {
            "utterance_id": 11,
            "interlocutor_id": "はくさい",
            "text": "@あずき ディズニー！",
            "mention_to": [
                "あずき"
            ]
        },
        {
            "utterance_id": 12,
            "interlocutor_id": "あずき",
            "text": "@はくさい ディズニーなら年齢幅広く",
            "mention_to": [
                "はくさい"
            ]
        },
        {
            "utterance_id": 13,
            "interlocutor_id": "あずき",
            "text": "楽しめそう",
            "mention_to": []
        },
        {
            "utterance_id": 14,
            "interlocutor_id": "はくさい",
            "text": "でも、私が行ったことなくて何もわからな過ぎて",
            "mention_to": []
        },
        {
            "utterance_id": 15,
            "interlocutor_id": "きなこ",
            "text": "うんうん楽しめますよね",
            "mention_to": []
        },
        {
            "utterance_id": 16,
            "interlocutor_id": "はくさい",
            "text": "行くに行けない。。。",
            "mention_to": []
        },
        {
            "utterance_id": 17,
            "interlocutor_id": "あずき",
            "text": "広いですよね",
            "mention_to": []
        },
        {
            "utterance_id": 18,
            "interlocutor_id": "あずき",
            "text": "意外と",
            "mention_to": []
        },
        {
            "utterance_id": 19,
            "interlocutor_id": "あずき",
            "text": "１日じゃ足りない",
            "mention_to": []
        },
        {
            "utterance_id": 20,
            "interlocutor_id": "きなこ",
            "text": "システムが・・コロコロ変わりますよね",
            "mention_to": []
        },
        {
            "utterance_id": 21,
            "interlocutor_id": "あずき",
            "text": "私も最新のファストパス？とか",
            "mention_to": []
        },
        {
            "utterance_id": 22,
            "interlocutor_id": "あずき",
            "text": "よくわからんです",
            "mention_to": []
        },
        {
            "utterance_id": 23,
            "interlocutor_id": "はくさい",
            "text": "そうなんですね",
            "mention_to": []
        },
        {
            "utterance_id": 24,
            "interlocutor_id": "あずき",
            "text": "でも去年行きました",
            "mention_to": []
        },
        {
            "utterance_id": 25,
            "interlocutor_id": "きなこ",
            "text": "そうそう",
            "mention_to": []
        },
        {
            "utterance_id": 26,
            "interlocutor_id": "あずき",
            "text": "娘の卒業旅行で",
            "mention_to": []
        },
        {
            "utterance_id": 27,
            "interlocutor_id": "はくさい",
            "text": "わかってる人に連れて行ってもらいたい",
            "mention_to": []
        },
        {
            "utterance_id": 28,
            "interlocutor_id": "あずき",
            "text": "二泊でシーとランド両方",
            "mention_to": []
        },
        {
            "utterance_id": 29,
            "interlocutor_id": "あずき",
            "text": "@はくさい わかる人と行った方がいいかも",
            "mention_to": [
                "はくさい"
            ]
        },
        {
            "utterance_id": 30,
            "interlocutor_id": "あずき",
            "text": "詳しい人はすごいですよね",
            "mention_to": []
        },
        {
            "utterance_id": 31,
            "interlocutor_id": "はくさい",
            "text": "@あずき 贅沢ですね～",
            "mention_to": [
                "あずき"
            ]
        },
        {
            "utterance_id": 32,
            "interlocutor_id": "あずき",
            "text": "マニアというか",
            "mention_to": []
        },
        {
            "utterance_id": 33,
            "interlocutor_id": "きなこ",
            "text": "@あずき いいですね～",
            "mention_to": [
                "あずき"
            ]
        },
        {
            "utterance_id": 34,
            "interlocutor_id": "あずき",
            "text": "一度なんでね",
            "mention_to": []
        },
        {
            "utterance_id": 35,
            "interlocutor_id": "あずき",
            "text": "奮発しました",
            "mention_to": []
        },
        {
            "utterance_id": 36,
            "interlocutor_id": "はくさい",
            "text": "すごい！！",
            "mention_to": []
        },
        {
            "utterance_id": 37,
            "interlocutor_id": "あずき",
            "text": "でもホテルは安いホテルですよ笑",
            "mention_to": []
        },
        {
            "utterance_id": 38,
            "interlocutor_id": "あずき",
            "text": "そもそも入園料が高い",
            "mention_to": []
        },
        {
            "utterance_id": 39,
            "interlocutor_id": "きなこ",
            "text": "楽しめましたか？",
            "mention_to": []
        },
        {
            "utterance_id": 40,
            "interlocutor_id": "あずき",
            "text": "楽しめました〜",
            "mention_to": []
        },
        {
            "utterance_id": 41,
            "interlocutor_id": "はくさい",
            "text": "いいですね",
            "mention_to": []
        },
        {
            "utterance_id": 42,
            "interlocutor_id": "きなこ",
            "text": "いいなあ～",
            "mention_to": []
        },
        {
            "utterance_id": 43,
            "interlocutor_id": "はくさい",
            "text": "何がおすすめですか？",
            "mention_to": []
        },
        {
            "utterance_id": 44,
            "interlocutor_id": "あずき",
            "text": "うちはランドの方が好きみたいです",
            "mention_to": []
        },
        {
            "utterance_id": 45,
            "interlocutor_id": "きなこ",
            "text": "うちもランド派",
            "mention_to": []
        },
        {
            "utterance_id": 46,
            "interlocutor_id": "あずき",
            "text": "ジェットコースター系は何度も",
            "mention_to": []
        },
        {
            "utterance_id": 47,
            "interlocutor_id": "あずき",
            "text": "並んで乗ってましたよ",
            "mention_to": []
        },
        {
            "utterance_id": 48,
            "interlocutor_id": "あずき",
            "text": "夜のパレードも",
            "mention_to": []
        },
        {
            "utterance_id": 49,
            "interlocutor_id": "きなこ",
            "text": "シーは乗り物怖くて・・",
            "mention_to": []
        },
        {
            "utterance_id": 50,
            "interlocutor_id": "あずき",
            "text": "綺麗でした",
            "mention_to": []
        },
        {
            "utterance_id": 51,
            "interlocutor_id": "きなこ",
            "text": "素敵ですよね",
            "mention_to": []
        },
        {
            "utterance_id": 52,
            "interlocutor_id": "あずき",
            "text": "@きなこ シーの方が大人向け",
            "mention_to": [
                "きなこ"
            ]
        },
        {
            "utterance_id": 53,
            "interlocutor_id": "あずき",
            "text": "ですかね",
            "mention_to": []
        },
        {
            "utterance_id": 54,
            "interlocutor_id": "きなこ",
            "text": "ですよね～",
            "mention_to": []
        },
        {
            "utterance_id": 55,
            "interlocutor_id": "あずき",
            "text": "私は乗り物乗らずに",
            "mention_to": []
        },
        {
            "utterance_id": 56,
            "interlocutor_id": "あずき",
            "text": "パレードの場所取りしてました",
            "mention_to": []
        },
        {
            "utterance_id": 57,
            "interlocutor_id": "きなこ",
            "text": "大変ですね！",
            "mention_to": []
        },
        {
            "utterance_id": 58,
            "interlocutor_id": "はくさい",
            "text": "パレードの場所取りも大変そう",
            "mention_to": []
        },
        {
            "utterance_id": 59,
            "interlocutor_id": "あずき",
            "text": "大変です",
            "mention_to": []
        },
        {
            "utterance_id": 60,
            "interlocutor_id": "あずき",
            "text": "疲れましたよ",
            "mention_to": []
        },
        {
            "utterance_id": 61,
            "interlocutor_id": "あずき",
            "text": "三連休？とかだったんで",
            "mention_to": []
        },
        {
            "utterance_id": 62,
            "interlocutor_id": "あずき",
            "text": "すごい人で",
            "mention_to": []
        },
        {
            "utterance_id": 63,
            "interlocutor_id": "はくさい",
            "text": "ここがいいって決めて場所取りするんですか？",
            "mention_to": []
        },
        {
            "utterance_id": 64,
            "interlocutor_id": "あずき",
            "text": "@はくさい なんとなくで場所取りしました",
            "mention_to": [
                "はくさい"
            ]
        },
        {
            "utterance_id": 65,
            "interlocutor_id": "あずき",
            "text": "座って見たかったんで",
            "mention_to": []
        },
        {
            "utterance_id": 66,
            "interlocutor_id": "はくさい",
            "text": "@あずき そうなんですね",
            "mention_to": [
                "あずき"
            ]
        },
        {
            "utterance_id": 67,
            "interlocutor_id": "あずき",
            "text": "やっぱり若者が多いですし",
            "mention_to": []
        },
        {
            "utterance_id": 68,
            "interlocutor_id": "はくさい",
            "text": "いろんなスケジュール考えて動かないと",
            "mention_to": []
        },
        {
            "utterance_id": 69,
            "interlocutor_id": "はくさい",
            "text": "人だけ見て終わっちゃいそうですね。。。",
            "mention_to": []
        },
        {
            "utterance_id": 70,
            "interlocutor_id": "きなこ",
            "text": "うちはパレードのスキに乗り物乗ってました",
            "mention_to": []
        },
        {
            "utterance_id": 71,
            "interlocutor_id": "あずき",
            "text": "@きなこ そうなんですねー",
            "mention_to": [
                "きなこ"
            ]
        },
        {
            "utterance_id": 72,
            "interlocutor_id": "あずき",
            "text": "それもありかも",
            "mention_to": []
        },
        {
            "utterance_id": 73,
            "interlocutor_id": "はくさい",
            "text": "@きなこ そういうのもあるんですね",
            "mention_to": [
                "きなこ"
            ]
        },
        {
            "utterance_id": 74,
            "interlocutor_id": "きなこ",
            "text": "子供が男子なので",
            "mention_to": []
        },
        {
            "utterance_id": 75,
            "interlocutor_id": "あずき",
            "text": "本当に並ぶ",
            "mention_to": []
        },
        {
            "utterance_id": 76,
            "interlocutor_id": "あずき",
            "text": "待ち時間も多いですよね",
            "mention_to": []
        },
        {
            "utterance_id": 77,
            "interlocutor_id": "きなこ",
            "text": "乗り物派",
            "mention_to": []
        },
        {
            "utterance_id": 78,
            "interlocutor_id": "きなこ",
            "text": "ですよね～",
            "mention_to": []
        },
        {
            "utterance_id": 79,
            "interlocutor_id": "あずき",
            "text": "確かに男子は乗り物だ",
            "mention_to": []
        },
        {
            "utterance_id": 80,
            "interlocutor_id": "はくさい",
            "text": "男子と女子の好みの違いもあるのかー",
            "mention_to": []
        },
        {
            "utterance_id": 81,
            "interlocutor_id": "あずき",
            "text": "ありますねー",
            "mention_to": []
        },
        {
            "utterance_id": 82,
            "interlocutor_id": "あずき",
            "text": "でも女子もディズニーの乗り物は意外と好きですね",
            "mention_to": []
        },
        {
            "utterance_id": 83,
            "interlocutor_id": "はくさい",
            "text": "@あずき そうなんですね",
            "mention_to": [
                "あずき"
            ]
        },
        {
            "utterance_id": 84,
            "interlocutor_id": "あずき",
            "text": "私はショーとか見て食事を楽しみたい",
            "mention_to": []
        },
        {
            "utterance_id": 85,
            "interlocutor_id": "あずき",
            "text": "のんびり周りたいです",
            "mention_to": []
        },
        {
            "utterance_id": 86,
            "interlocutor_id": "あずき",
            "text": "子供いれば難しいですけどね",
            "mention_to": []
        },
        {
            "utterance_id": 87,
            "interlocutor_id": "はくさい",
            "text": "こうやって聞いてるだけでも、選択肢が多すぎて",
            "mention_to": []
        },
        {
            "utterance_id": 88,
            "interlocutor_id": "あずき",
            "text": "うんうん",
            "mention_to": []
        },
        {
            "utterance_id": 89,
            "interlocutor_id": "はくさい",
            "text": "一回じゃやりきれないですね",
            "mention_to": []
        },
        {
            "utterance_id": 90,
            "interlocutor_id": "あずき",
            "text": "そうなんですよー",
            "mention_to": []
        },
        {
            "utterance_id": 91,
            "interlocutor_id": "きなこ",
            "text": "本当ですね",
            "mention_to": []
        },
        {
            "utterance_id": 92,
            "interlocutor_id": "あずき",
            "text": "結局、全部は無理ですよね",
            "mention_to": []
        },
        {
            "utterance_id": 93,
            "interlocutor_id": "はくさい",
            "text": "厳しそうですね",
            "mention_to": []
        },
        {
            "utterance_id": 94,
            "interlocutor_id": "あずき",
            "text": "でも新しくラプンチェル？とか",
            "mention_to": []
        },
        {
            "utterance_id": 95,
            "interlocutor_id": "あずき",
            "text": "アナ雪のできますよね",
            "mention_to": []
        },
        {
            "utterance_id": 96,
            "interlocutor_id": "あずき",
            "text": "六月位？",
            "mention_to": []
        },
        {
            "utterance_id": 97,
            "interlocutor_id": "きなこ",
            "text": "そうなんですね！",
            "mention_to": []
        },
        {
            "utterance_id": 98,
            "interlocutor_id": "はくさい",
            "text": "@あずき そうなんですか？",
            "mention_to": [
                "あずき"
            ]
        },
        {
            "utterance_id": 99,
            "interlocutor_id": "あずき",
            "text": "そこも楽しめそう",
            "mention_to": []
        },
        {
            "utterance_id": 100,
            "interlocutor_id": "あずき",
            "text": "テレビで見ました",
            "mention_to": []
        },
        {
            "utterance_id": 101,
            "interlocutor_id": "きなこ",
            "text": "早速行ってみようかな",
            "mention_to": []
        },
        {
            "utterance_id": 102,
            "interlocutor_id": "あずき",
            "text": "シー？だったかな？",
            "mention_to": []
        },
        {
            "utterance_id": 103,
            "interlocutor_id": "あずき",
            "text": "いいですね！！",
            "mention_to": []
        },
        {
            "utterance_id": 104,
            "interlocutor_id": "はくさい",
            "text": "もっと近く人住んでたら",
            "mention_to": []
        },
        {
            "utterance_id": 105,
            "interlocutor_id": "はくさい",
            "text": "あんまり考えずにいけそう",
            "mention_to": []
        },
        {
            "utterance_id": 106,
            "interlocutor_id": "あずき",
            "text": "@はくさい 同じくです",
            "mention_to": [
                "はくさい"
            ]
        }
    ],
    "evaluations": [
        {
            "interlocutor_id": "はくさい",
            "informativeness": 5,
            "comprehension": 5,
            "familiarity": 5,
            "interest": 5,
            "proactiveness": 5,
            "satisfaction": 5
        },
        {
            "interlocutor_id": "あずき",
            "informativeness": 4,
            "comprehension": 4,
            "familiarity": 5,
            "interest": 5,
            "proactiveness": 5,
            "satisfaction": 5
        },
        {
            "interlocutor_id": "きなこ",
            "informativeness": 5,
            "comprehension": 5,
            "familiarity": 5,
            "interest": 5,
            "proactiveness": 5,
            "satisfaction": 5
        }
    ]
}