{
    "dialogue_id": "A06403",
    "dialogue_type": "First time",
    "interlocutors": [
        "あざらし",
        "あまえび",
        "あひる"
    ],
    "relationship": [],
    "utterances": [
        {
            "utterance_id": 0,
            "interlocutor_id": "あざらし",
            "text": "こんばんは！",
            "mention_to": []
        },
        {
            "utterance_id": 1,
            "interlocutor_id": "あまえび",
            "text": "こんばんは",
            "mention_to": []
        },
        {
            "utterance_id": 2,
            "interlocutor_id": "あひる",
            "text": "こんばんは！",
            "mention_to": []
        },
        {
            "utterance_id": 3,
            "interlocutor_id": "あざらし",
            "text": "最近、オートファジーをしてます",
            "mention_to": []
        },
        {
            "utterance_id": 4,
            "interlocutor_id": "あひる",
            "text": "おぉー！！",
            "mention_to": []
        },
        {
            "utterance_id": 5,
            "interlocutor_id": "あざらし",
            "text": "16時間断食ってやつです",
            "mention_to": []
        },
        {
            "utterance_id": 6,
            "interlocutor_id": "あまえび",
            "text": "そうなんですね",
            "mention_to": []
        },
        {
            "utterance_id": 7,
            "interlocutor_id": "あざらし",
            "text": "始めたばかりで",
            "mention_to": []
        },
        {
            "utterance_id": 8,
            "interlocutor_id": "あひる",
            "text": "本で読んだことある！！",
            "mention_to": []
        },
        {
            "utterance_id": 9,
            "interlocutor_id": "あざらし",
            "text": "効果はまだ出てないんですが",
            "mention_to": []
        },
        {
            "utterance_id": 10,
            "interlocutor_id": "あひる",
            "text": "うんうん",
            "mention_to": []
        },
        {
            "utterance_id": 11,
            "interlocutor_id": "あざらし",
            "text": "ダイエットにいいとかで",
            "mention_to": []
        },
        {
            "utterance_id": 12,
            "interlocutor_id": "あまえび",
            "text": "うんうん",
            "mention_to": []
        },
        {
            "utterance_id": 13,
            "interlocutor_id": "あざらし",
            "text": "最近、慣れてきました",
            "mention_to": []
        },
        {
            "utterance_id": 14,
            "interlocutor_id": "あひる",
            "text": "@あざらし 実践してすごいです！！",
            "mention_to": [
                "あざらし"
            ]
        },
        {
            "utterance_id": 15,
            "interlocutor_id": "あざらし",
            "text": "20時以降は水分だけです",
            "mention_to": []
        },
        {
            "utterance_id": 16,
            "interlocutor_id": "あひる",
            "text": "ひぇー！！",
            "mention_to": []
        },
        {
            "utterance_id": 17,
            "interlocutor_id": "あまえび",
            "text": "それは大変",
            "mention_to": []
        },
        {
            "utterance_id": 18,
            "interlocutor_id": "あざらし",
            "text": "お昼の12時以降に最初の食事",
            "mention_to": []
        },
        {
            "utterance_id": 19,
            "interlocutor_id": "あざらし",
            "text": "をします",
            "mention_to": []
        },
        {
            "utterance_id": 20,
            "interlocutor_id": "あまえび",
            "text": "うんうん",
            "mention_to": []
        },
        {
            "utterance_id": 21,
            "interlocutor_id": "あざらし",
            "text": "なんとか痩せたい汗",
            "mention_to": []
        },
        {
            "utterance_id": 22,
            "interlocutor_id": "あまえび",
            "text": "わたしも",
            "mention_to": []
        },
        {
            "utterance_id": 23,
            "interlocutor_id": "あひる",
            "text": "@あざらし 朝の過ごし方はなにか気をつけることあるんですか？",
            "mention_to": [
                "あざらし"
            ]
        },
        {
            "utterance_id": 24,
            "interlocutor_id": "あひる",
            "text": "運動するとか！",
            "mention_to": []
        },
        {
            "utterance_id": 25,
            "interlocutor_id": "あざらし",
            "text": "運動してないんですよー",
            "mention_to": []
        },
        {
            "utterance_id": 26,
            "interlocutor_id": "あひる",
            "text": "なるほどです！",
            "mention_to": []
        },
        {
            "utterance_id": 27,
            "interlocutor_id": "あざらし",
            "text": "朝は水分だけです",
            "mention_to": []
        },
        {
            "utterance_id": 28,
            "interlocutor_id": "あひる",
            "text": "でも何も食べずにすごい...！",
            "mention_to": []
        },
        {
            "utterance_id": 29,
            "interlocutor_id": "あざらし",
            "text": "カフェインも摂らないように",
            "mention_to": []
        },
        {
            "utterance_id": 30,
            "interlocutor_id": "あざらし",
            "text": "しています",
            "mention_to": []
        },
        {
            "utterance_id": 31,
            "interlocutor_id": "あひる",
            "text": "ひぇー！",
            "mention_to": []
        },
        {
            "utterance_id": 32,
            "interlocutor_id": "あざらし",
            "text": "でも",
            "mention_to": []
        },
        {
            "utterance_id": 33,
            "interlocutor_id": "あまえび",
            "text": "カフェインダメなんですね。",
            "mention_to": []
        },
        {
            "utterance_id": 34,
            "interlocutor_id": "あざらし",
            "text": "慣れますよ",
            "mention_to": []
        },
        {
            "utterance_id": 35,
            "interlocutor_id": "あまえび",
            "text": "そうなんだ",
            "mention_to": []
        },
        {
            "utterance_id": 36,
            "interlocutor_id": "あひる",
            "text": "慣れかぁ...",
            "mention_to": []
        },
        {
            "utterance_id": 37,
            "interlocutor_id": "あざらし",
            "text": "@あまえび だめみたいですね",
            "mention_to": [
                "あまえび"
            ]
        },
        {
            "utterance_id": 38,
            "interlocutor_id": "あざらし",
            "text": "空っぽの胃に良くないのかな",
            "mention_to": []
        },
        {
            "utterance_id": 39,
            "interlocutor_id": "あひる",
            "text": "わたしも2回くらいやったのですが、",
            "mention_to": []
        },
        {
            "utterance_id": 40,
            "interlocutor_id": "あまえび",
            "text": "@あざらし そうなると、ハードル高いな",
            "mention_to": [
                "あざらし"
            ]
        },
        {
            "utterance_id": 41,
            "interlocutor_id": "あざらし",
            "text": "@あひる おおー",
            "mention_to": [
                "あひる"
            ]
        },
        {
            "utterance_id": 42,
            "interlocutor_id": "あひる",
            "text": "食べた過ぎて全然続かなくて",
            "mention_to": []
        },
        {
            "utterance_id": 43,
            "interlocutor_id": "あまえび",
            "text": "うんうん",
            "mention_to": []
        },
        {
            "utterance_id": 44,
            "interlocutor_id": "あざらし",
            "text": "そうでした？",
            "mention_to": []
        },
        {
            "utterance_id": 45,
            "interlocutor_id": "あざらし",
            "text": "どうでした？",
            "mention_to": []
        },
        {
            "utterance_id": 46,
            "interlocutor_id": "あひる",
            "text": "もうね、食べちゃうの 笑笑",
            "mention_to": []
        },
        {
            "utterance_id": 47,
            "interlocutor_id": "あざらし",
            "text": "そうなんですねー",
            "mention_to": []
        },
        {
            "utterance_id": 48,
            "interlocutor_id": "あひる",
            "text": "だから尊敬しますー！",
            "mention_to": []
        },
        {
            "utterance_id": 49,
            "interlocutor_id": "あざらし",
            "text": "いえいえ",
            "mention_to": []
        },
        {
            "utterance_id": 50,
            "interlocutor_id": "あまえび",
            "text": "本当に尊敬",
            "mention_to": []
        },
        {
            "utterance_id": 51,
            "interlocutor_id": "あざらし",
            "text": "まだ始めたばかりなので",
            "mention_to": []
        },
        {
            "utterance_id": 52,
            "interlocutor_id": "あひる",
            "text": "うんうん！",
            "mention_to": []
        },
        {
            "utterance_id": 53,
            "interlocutor_id": "あざらし",
            "text": "脱落するかもしれません",
            "mention_to": []
        },
        {
            "utterance_id": 54,
            "interlocutor_id": "あまえび",
            "text": "自制できるのがすごい！",
            "mention_to": []
        },
        {
            "utterance_id": 55,
            "interlocutor_id": "あまえび",
            "text": "尊敬です",
            "mention_to": []
        },
        {
            "utterance_id": 56,
            "interlocutor_id": "あひる",
            "text": "ほんとほんと！",
            "mention_to": []
        },
        {
            "utterance_id": 57,
            "interlocutor_id": "あざらし",
            "text": "いえいえ、",
            "mention_to": []
        },
        {
            "utterance_id": 58,
            "interlocutor_id": "あざらし",
            "text": "何かしないと",
            "mention_to": []
        },
        {
            "utterance_id": 59,
            "interlocutor_id": "あざらし",
            "text": "本当に危険！！",
            "mention_to": []
        },
        {
            "utterance_id": 60,
            "interlocutor_id": "あまえび",
            "text": "わたしも見習います",
            "mention_to": []
        },
        {
            "utterance_id": 61,
            "interlocutor_id": "あまえび",
            "text": "わたしも危険",
            "mention_to": []
        },
        {
            "utterance_id": 62,
            "interlocutor_id": "あざらし",
            "text": "来年の健康診断が心配で",
            "mention_to": []
        },
        {
            "utterance_id": 63,
            "interlocutor_id": "あひる",
            "text": "わたしも改めてチャレンジしますっ",
            "mention_to": []
        },
        {
            "utterance_id": 64,
            "interlocutor_id": "あひる",
            "text": "@あざらし うんうん",
            "mention_to": [
                "あざらし"
            ]
        },
        {
            "utterance_id": 65,
            "interlocutor_id": "あざらし",
            "text": "お腹周りが",
            "mention_to": []
        },
        {
            "utterance_id": 66,
            "interlocutor_id": "あざらし",
            "text": "どんどん",
            "mention_to": []
        },
        {
            "utterance_id": 67,
            "interlocutor_id": "あひる",
            "text": "お腹周り気になる〜",
            "mention_to": []
        },
        {
            "utterance_id": 68,
            "interlocutor_id": "あざらし",
            "text": "すごいことに汗",
            "mention_to": []
        },
        {
            "utterance_id": 69,
            "interlocutor_id": "あひる",
            "text": "昔より代謝落ちた気がして、",
            "mention_to": []
        },
        {
            "utterance_id": 70,
            "interlocutor_id": "あひる",
            "text": "太った気がする...",
            "mention_to": []
        },
        {
            "utterance_id": 71,
            "interlocutor_id": "あざらし",
            "text": "@あひる 落ちましたねー",
            "mention_to": [
                "あひる"
            ]
        },
        {
            "utterance_id": 72,
            "interlocutor_id": "あまえび",
            "text": "まさにわたしがそう",
            "mention_to": []
        },
        {
            "utterance_id": 73,
            "interlocutor_id": "あざらし",
            "text": "代謝がね",
            "mention_to": []
        },
        {
            "utterance_id": 74,
            "interlocutor_id": "あひる",
            "text": "そうよねよね〜",
            "mention_to": []
        },
        {
            "utterance_id": 75,
            "interlocutor_id": "あざらし",
            "text": "若い子は寝ているだけで",
            "mention_to": []
        },
        {
            "utterance_id": 76,
            "interlocutor_id": "あひる",
            "text": "わたしもやらなきゃな、",
            "mention_to": []
        },
        {
            "utterance_id": 77,
            "interlocutor_id": "あざらし",
            "text": "痩せられるとか？",
            "mention_to": []
        },
        {
            "utterance_id": 78,
            "interlocutor_id": "あひる",
            "text": "@あざらし そうそう！！！",
            "mention_to": [
                "あざらし"
            ]
        },
        {
            "utterance_id": 79,
            "interlocutor_id": "あまえび",
            "text": "昔は3キロとかすぐに落とせたんだけど",
            "mention_to": []
        },
        {
            "utterance_id": 80,
            "interlocutor_id": "あざらし",
            "text": "羨ましい限りです",
            "mention_to": []
        },
        {
            "utterance_id": 81,
            "interlocutor_id": "あひる",
            "text": "うんうん",
            "mention_to": []
        },
        {
            "utterance_id": 82,
            "interlocutor_id": "あざらし",
            "text": "@あまえび ええ",
            "mention_to": [
                "あまえび"
            ]
        },
        {
            "utterance_id": 83,
            "interlocutor_id": "あまえび",
            "text": "今は全然ダメ",
            "mention_to": []
        },
        {
            "utterance_id": 84,
            "interlocutor_id": "あひる",
            "text": "ねー",
            "mention_to": []
        },
        {
            "utterance_id": 85,
            "interlocutor_id": "あざらし",
            "text": "@あまえび そうなんですよねー",
            "mention_to": [
                "あまえび"
            ]
        },
        {
            "utterance_id": 86,
            "interlocutor_id": "あざらし",
            "text": "びくともしません",
            "mention_to": []
        },
        {
            "utterance_id": 87,
            "interlocutor_id": "あまえび",
            "text": "@あざらし なんとかしなければ！",
            "mention_to": [
                "あざらし"
            ]
        },
        {
            "utterance_id": 88,
            "interlocutor_id": "あまえび",
            "text": "見習います！",
            "mention_to": []
        },
        {
            "utterance_id": 89,
            "interlocutor_id": "あざらし",
            "text": "リバウンドもすぐですよね",
            "mention_to": []
        },
        {
            "utterance_id": 90,
            "interlocutor_id": "あひる",
            "text": "むしろ増えるしぼう",
            "mention_to": []
        },
        {
            "utterance_id": 91,
            "interlocutor_id": "あまえび",
            "text": "わたしリバウンドしました。",
            "mention_to": []
        },
        {
            "utterance_id": 92,
            "interlocutor_id": "あざらし",
            "text": "なんなんですかね",
            "mention_to": []
        },
        {
            "utterance_id": 93,
            "interlocutor_id": "あひる",
            "text": "そう！リバウンド",
            "mention_to": []
        },
        {
            "utterance_id": 94,
            "interlocutor_id": "あひる",
            "text": "なんなんでしょうかね",
            "mention_to": []
        },
        {
            "utterance_id": 95,
            "interlocutor_id": "あまえび",
            "text": "でも、絶対また落とす！",
            "mention_to": []
        },
        {
            "utterance_id": 96,
            "interlocutor_id": "あまえび",
            "text": "誓います！",
            "mention_to": []
        },
        {
            "utterance_id": 97,
            "interlocutor_id": "あざらし",
            "text": "そんなに食べてるもの変わらないのに",
            "mention_to": []
        },
        {
            "utterance_id": 98,
            "interlocutor_id": "あまえび",
            "text": "笑",
            "mention_to": []
        },
        {
            "utterance_id": 99,
            "interlocutor_id": "あざらし",
            "text": "@あまえび おお！！",
            "mention_to": [
                "あまえび"
            ]
        },
        {
            "utterance_id": 100,
            "interlocutor_id": "あざらし",
            "text": "いいですね",
            "mention_to": []
        },
        {
            "utterance_id": 101,
            "interlocutor_id": "あざらし",
            "text": "やる気になった時が",
            "mention_to": []
        },
        {
            "utterance_id": 102,
            "interlocutor_id": "あひる",
            "text": "がんばろっ！！",
            "mention_to": []
        },
        {
            "utterance_id": 103,
            "interlocutor_id": "あざらし",
            "text": "始どきです",
            "mention_to": []
        }
    ],
    "evaluations": [
        {
            "interlocutor_id": "あざらし",
            "informativeness": 3,
            "comprehension": 4,
            "familiarity": 4,
            "interest": 4,
            "proactiveness": 4,
            "satisfaction": 3
        },
        {
            "interlocutor_id": "あまえび",
            "informativeness": 5,
            "comprehension": 5,
            "familiarity": 5,
            "interest": 5,
            "proactiveness": 5,
            "satisfaction": 5
        },
        {
            "interlocutor_id": "あひる",
            "informativeness": 5,
            "comprehension": 5,
            "familiarity": 5,
            "interest": 5,
            "proactiveness": 5,
            "satisfaction": 5
        }
    ]
}