{
    "dialogue_id": "A09702",
    "dialogue_type": "First time",
    "interlocutors": [
        "おにぎり",
        "ハンバーグ",
        "らっこ"
    ],
    "relationship": [],
    "utterances": [
        {
            "utterance_id": 0,
            "interlocutor_id": "おにぎり",
            "text": "こんにちは。",
            "mention_to": []
        },
        {
            "utterance_id": 1,
            "interlocutor_id": "ハンバーグ",
            "text": "こんにちは",
            "mention_to": []
        },
        {
            "utterance_id": 2,
            "interlocutor_id": "らっこ",
            "text": "こんにちはー",
            "mention_to": []
        },
        {
            "utterance_id": 3,
            "interlocutor_id": "おにぎり",
            "text": "よろしくお願いいたします。",
            "mention_to": []
        },
        {
            "utterance_id": 4,
            "interlocutor_id": "ハンバーグ",
            "text": "よろしくお願いします",
            "mention_to": []
        },
        {
            "utterance_id": 5,
            "interlocutor_id": "らっこ",
            "text": "よろしくおねがいしますー",
            "mention_to": []
        },
        {
            "utterance_id": 6,
            "interlocutor_id": "おにぎり",
            "text": "もう、3月ですねぇ。",
            "mention_to": []
        },
        {
            "utterance_id": 7,
            "interlocutor_id": "ハンバーグ",
            "text": "ですね",
            "mention_to": []
        },
        {
            "utterance_id": 8,
            "interlocutor_id": "おにぎり",
            "text": "何か、3月は予定とかイベントありますか？",
            "mention_to": []
        },
        {
            "utterance_id": 9,
            "interlocutor_id": "ハンバーグ",
            "text": "だいぶ早く感じます",
            "mention_to": []
        },
        {
            "utterance_id": 10,
            "interlocutor_id": "ハンバーグ",
            "text": "@おにぎり 特にないかな",
            "mention_to": [
                "おにぎり"
            ]
        },
        {
            "utterance_id": 11,
            "interlocutor_id": "おにぎり",
            "text": "あっという間ですねぇ！！",
            "mention_to": []
        },
        {
            "utterance_id": 12,
            "interlocutor_id": "らっこ",
            "text": "卒業式でした。",
            "mention_to": []
        },
        {
            "utterance_id": 13,
            "interlocutor_id": "ハンバーグ",
            "text": "ですです",
            "mention_to": []
        },
        {
            "utterance_id": 14,
            "interlocutor_id": "おにぎり",
            "text": "@らっこ 卒業式！おめでとうございます！",
            "mention_to": [
                "らっこ"
            ]
        },
        {
            "utterance_id": 15,
            "interlocutor_id": "ハンバーグ",
            "text": "@らっこ おめでとうございます",
            "mention_to": [
                "らっこ"
            ]
        },
        {
            "utterance_id": 16,
            "interlocutor_id": "らっこ",
            "text": "ありがとうございます。",
            "mention_to": []
        },
        {
            "utterance_id": 17,
            "interlocutor_id": "おにぎり",
            "text": "参加したのですか？",
            "mention_to": []
        },
        {
            "utterance_id": 18,
            "interlocutor_id": "らっこ",
            "text": "はい。出席しました。",
            "mention_to": []
        },
        {
            "utterance_id": 19,
            "interlocutor_id": "おにぎり",
            "text": "泣いちゃいました？",
            "mention_to": []
        },
        {
            "utterance_id": 20,
            "interlocutor_id": "らっこ",
            "text": "意外と、保護者多くてビックリしました。",
            "mention_to": []
        },
        {
            "utterance_id": 21,
            "interlocutor_id": "ハンバーグ",
            "text": "そうなんですね",
            "mention_to": []
        },
        {
            "utterance_id": 22,
            "interlocutor_id": "らっこ",
            "text": "ぜんぜん。そんな感じじゃないですね。",
            "mention_to": []
        },
        {
            "utterance_id": 23,
            "interlocutor_id": "おにぎり",
            "text": "そうなんですか！",
            "mention_to": []
        },
        {
            "utterance_id": 24,
            "interlocutor_id": "ハンバーグ",
            "text": "高校ですか？",
            "mention_to": []
        },
        {
            "utterance_id": 25,
            "interlocutor_id": "らっこ",
            "text": "高校です。卒業できてよかった。",
            "mention_to": []
        },
        {
            "utterance_id": 26,
            "interlocutor_id": "らっこ",
            "text": "最後、ギリギリの成績だったので心配しました。",
            "mention_to": []
        },
        {
            "utterance_id": 27,
            "interlocutor_id": "ハンバーグ",
            "text": "なるほど",
            "mention_to": []
        },
        {
            "utterance_id": 28,
            "interlocutor_id": "おにぎり",
            "text": "高校だとそんな感じでしたっけ。",
            "mention_to": []
        },
        {
            "utterance_id": 29,
            "interlocutor_id": "おにぎり",
            "text": "良かった！良かった！！！",
            "mention_to": []
        },
        {
            "utterance_id": 30,
            "interlocutor_id": "ハンバーグ",
            "text": "卒業できてよかったですね",
            "mention_to": []
        },
        {
            "utterance_id": 31,
            "interlocutor_id": "ハンバーグ",
            "text": "進学ですか？",
            "mention_to": []
        },
        {
            "utterance_id": 32,
            "interlocutor_id": "おにぎり",
            "text": "高校は、その心配があるのでしたねぇ。。",
            "mention_to": []
        },
        {
            "utterance_id": 33,
            "interlocutor_id": "らっこ",
            "text": "進学です。",
            "mention_to": []
        },
        {
            "utterance_id": 34,
            "interlocutor_id": "ハンバーグ",
            "text": "就職？",
            "mention_to": []
        },
        {
            "utterance_id": 35,
            "interlocutor_id": "おにぎり",
            "text": "大学受験は大変でしたか？",
            "mention_to": []
        },
        {
            "utterance_id": 36,
            "interlocutor_id": "らっこ",
            "text": "今、部活仲間と旅行中です。",
            "mention_to": []
        },
        {
            "utterance_id": 37,
            "interlocutor_id": "ハンバーグ",
            "text": "@らっこ じゃまだお金かかりますねー",
            "mention_to": [
                "らっこ"
            ]
        },
        {
            "utterance_id": 38,
            "interlocutor_id": "らっこ",
            "text": "はい。まだまだですね",
            "mention_to": []
        },
        {
            "utterance_id": 39,
            "interlocutor_id": "おにぎり",
            "text": "お金ーーー。。",
            "mention_to": []
        },
        {
            "utterance_id": 40,
            "interlocutor_id": "ハンバーグ",
            "text": "@らっこ いい思い出つくりですね",
            "mention_to": [
                "らっこ"
            ]
        },
        {
            "utterance_id": 41,
            "interlocutor_id": "らっこ",
            "text": "楽しそうです。自由で。",
            "mention_to": []
        },
        {
            "utterance_id": 42,
            "interlocutor_id": "おにぎり",
            "text": "楽しい時ですね～いいな～！",
            "mention_to": []
        },
        {
            "utterance_id": 43,
            "interlocutor_id": "らっこ",
            "text": "富士急ハイランドに行ってます",
            "mention_to": []
        },
        {
            "utterance_id": 44,
            "interlocutor_id": "ハンバーグ",
            "text": "学生に戻りたい気持ちもありますよね",
            "mention_to": []
        },
        {
            "utterance_id": 45,
            "interlocutor_id": "ハンバーグ",
            "text": "@らっこ いいなぁ",
            "mention_to": [
                "らっこ"
            ]
        },
        {
            "utterance_id": 46,
            "interlocutor_id": "おにぎり",
            "text": "富士急！楽しそう～！！",
            "mention_to": []
        },
        {
            "utterance_id": 47,
            "interlocutor_id": "らっこ",
            "text": "絶叫系ばっかりらしいですね",
            "mention_to": []
        },
        {
            "utterance_id": 48,
            "interlocutor_id": "おにぎり",
            "text": "高校とか大学なら、戻りたいな！",
            "mention_to": []
        },
        {
            "utterance_id": 49,
            "interlocutor_id": "ハンバーグ",
            "text": "富士急は絶叫系無理な人は厳しそう",
            "mention_to": []
        },
        {
            "utterance_id": 50,
            "interlocutor_id": "おにぎり",
            "text": "富士急は絶叫系に乗れる人は、最高ですよね。",
            "mention_to": []
        },
        {
            "utterance_id": 51,
            "interlocutor_id": "らっこ",
            "text": "ですね。",
            "mention_to": []
        },
        {
            "utterance_id": 52,
            "interlocutor_id": "おにぎり",
            "text": "皆さん、お好きですか？",
            "mention_to": []
        },
        {
            "utterance_id": 53,
            "interlocutor_id": "らっこ",
            "text": "私は今はもう無理かなー",
            "mention_to": []
        },
        {
            "utterance_id": 54,
            "interlocutor_id": "ハンバーグ",
            "text": "@おにぎり 乗ろうと思えばのれます笑",
            "mention_to": [
                "おにぎり"
            ]
        },
        {
            "utterance_id": 55,
            "interlocutor_id": "おにぎり",
            "text": "昔は、乗れたけど、私も今は、ビックサンダーマウンテンまでです。。",
            "mention_to": []
        },
        {
            "utterance_id": 56,
            "interlocutor_id": "らっこ",
            "text": "わかる。",
            "mention_to": []
        },
        {
            "utterance_id": 57,
            "interlocutor_id": "らっこ",
            "text": "ビックサンダーマウンテンならいける",
            "mention_to": []
        },
        {
            "utterance_id": 58,
            "interlocutor_id": "ハンバーグ",
            "text": "@おにぎり ディズニーならいいですね",
            "mention_to": [
                "おにぎり"
            ]
        },
        {
            "utterance_id": 59,
            "interlocutor_id": "おにぎり",
            "text": "@ハンバーグ おぉ！若い！",
            "mention_to": [
                "ハンバーグ"
            ]
        },
        {
            "utterance_id": 60,
            "interlocutor_id": "らっこ",
            "text": "このまえUSJ行って",
            "mention_to": []
        },
        {
            "utterance_id": 61,
            "interlocutor_id": "おにぎり",
            "text": "ビックサンダーマウンテンは、楽しんで乗れますよね！",
            "mention_to": []
        },
        {
            "utterance_id": 62,
            "interlocutor_id": "ハンバーグ",
            "text": "@おにぎり 自分からはならないですけど笑",
            "mention_to": [
                "おにぎり"
            ]
        },
        {
            "utterance_id": 63,
            "interlocutor_id": "らっこ",
            "text": "知らずに怖いのに乗って、死ぬかと思いました。",
            "mention_to": []
        },
        {
            "utterance_id": 64,
            "interlocutor_id": "おにぎり",
            "text": "@ハンバーグ 付き添いでね！",
            "mention_to": [
                "ハンバーグ"
            ]
        },
        {
            "utterance_id": 65,
            "interlocutor_id": "おにぎり",
            "text": "@らっこ 怖いのあるんですね。ダイナソー何とか？",
            "mention_to": [
                "らっこ"
            ]
        },
        {
            "utterance_id": 66,
            "interlocutor_id": "ハンバーグ",
            "text": "一緒に乗ろってなれば乗ります",
            "mention_to": []
        },
        {
            "utterance_id": 67,
            "interlocutor_id": "らっこ",
            "text": "それです！ダイナソー",
            "mention_to": []
        },
        {
            "utterance_id": 68,
            "interlocutor_id": "おにぎり",
            "text": "あれ、怖いんですね~",
            "mention_to": []
        },
        {
            "utterance_id": 69,
            "interlocutor_id": "おにぎり",
            "text": "USJ行った事ないんです。",
            "mention_to": []
        },
        {
            "utterance_id": 70,
            "interlocutor_id": "ハンバーグ",
            "text": "最近行ってないから昔と全然変わってそう",
            "mention_to": []
        },
        {
            "utterance_id": 71,
            "interlocutor_id": "らっこ",
            "text": "足がぶらぶらしていて、踏ん張れなくてー",
            "mention_to": []
        },
        {
            "utterance_id": 72,
            "interlocutor_id": "おにぎり",
            "text": "ぶらぶら系かー。。。",
            "mention_to": []
        },
        {
            "utterance_id": 73,
            "interlocutor_id": "らっこ",
            "text": "@ハンバーグ どれぐらい前ですか？USF",
            "mention_to": [
                "ハンバーグ"
            ]
        },
        {
            "utterance_id": 74,
            "interlocutor_id": "らっこ",
            "text": "USJ",
            "mention_to": []
        },
        {
            "utterance_id": 75,
            "interlocutor_id": "ハンバーグ",
            "text": "USJもはるか昔だわら",
            "mention_to": []
        },
        {
            "utterance_id": 76,
            "interlocutor_id": "おにぎり",
            "text": "怖そう。",
            "mention_to": []
        },
        {
            "utterance_id": 77,
            "interlocutor_id": "おにぎり",
            "text": "@らっこ 良く行くんですか？",
            "mention_to": [
                "らっこ"
            ]
        },
        {
            "utterance_id": 78,
            "interlocutor_id": "ハンバーグ",
            "text": "@らっこ オープンしてまもなくだった気がするから",
            "mention_to": [
                "らっこ"
            ]
        },
        {
            "utterance_id": 79,
            "interlocutor_id": "らっこ",
            "text": "それはかなり前ですね。",
            "mention_to": []
        },
        {
            "utterance_id": 80,
            "interlocutor_id": "らっこ",
            "text": "変わっているはずです。",
            "mention_to": []
        },
        {
            "utterance_id": 81,
            "interlocutor_id": "おにぎり",
            "text": "もう、オープンしてけっこう経ちましたかね。。",
            "mention_to": []
        },
        {
            "utterance_id": 82,
            "interlocutor_id": "ハンバーグ",
            "text": "20年くらい前になりますかね….",
            "mention_to": []
        },
        {
            "utterance_id": 83,
            "interlocutor_id": "らっこ",
            "text": "20年ぐらいたってますよね。たぶん。",
            "mention_to": []
        },
        {
            "utterance_id": 84,
            "interlocutor_id": "おにぎり",
            "text": "USJも混んでますか？",
            "mention_to": []
        },
        {
            "utterance_id": 85,
            "interlocutor_id": "ハンバーグ",
            "text": "そりゃ年もとるわけだ笑",
            "mention_to": []
        },
        {
            "utterance_id": 86,
            "interlocutor_id": "らっこ",
            "text": "混んでましたUSJ",
            "mention_to": []
        },
        {
            "utterance_id": 87,
            "interlocutor_id": "おにぎり",
            "text": "笑笑",
            "mention_to": []
        },
        {
            "utterance_id": 88,
            "interlocutor_id": "ハンバーグ",
            "text": "混んでそう",
            "mention_to": []
        },
        {
            "utterance_id": 89,
            "interlocutor_id": "らっこ",
            "text": "でも、お金払って、並ばなくていいチケットを買ったので",
            "mention_to": []
        },
        {
            "utterance_id": 90,
            "interlocutor_id": "らっこ",
            "text": "快適でした。",
            "mention_to": []
        },
        {
            "utterance_id": 91,
            "interlocutor_id": "らっこ",
            "text": "高かったけど。",
            "mention_to": []
        },
        {
            "utterance_id": 92,
            "interlocutor_id": "ハンバーグ",
            "text": "ああ",
            "mention_to": []
        },
        {
            "utterance_id": 93,
            "interlocutor_id": "おにぎり",
            "text": "そういうシステムがあるのですね！",
            "mention_to": []
        },
        {
            "utterance_id": 94,
            "interlocutor_id": "ハンバーグ",
            "text": "確かにありますよね",
            "mention_to": []
        },
        {
            "utterance_id": 95,
            "interlocutor_id": "おにぎり",
            "text": "それは、良い。",
            "mention_to": []
        },
        {
            "utterance_id": 96,
            "interlocutor_id": "らっこ",
            "text": "お金で解決するシステムです。",
            "mention_to": []
        },
        {
            "utterance_id": 97,
            "interlocutor_id": "ハンバーグ",
            "text": "そうですね",
            "mention_to": []
        },
        {
            "utterance_id": 98,
            "interlocutor_id": "らっこ",
            "text": "いいけど、怖いですよ。",
            "mention_to": []
        },
        {
            "utterance_id": 99,
            "interlocutor_id": "ハンバーグ",
            "text": "結構な金額なんですか？",
            "mention_to": []
        },
        {
            "utterance_id": 100,
            "interlocutor_id": "おにぎり",
            "text": "たまにしか行かないなら、なるべく乗りたいですもんね。",
            "mention_to": []
        },
        {
            "utterance_id": 101,
            "interlocutor_id": "ハンバーグ",
            "text": "ですです",
            "mention_to": []
        },
        {
            "utterance_id": 102,
            "interlocutor_id": "らっこ",
            "text": "4人で13万円ぐらい使いました。",
            "mention_to": []
        },
        {
            "utterance_id": 103,
            "interlocutor_id": "らっこ",
            "text": "チケット代だけで",
            "mention_to": []
        },
        {
            "utterance_id": 104,
            "interlocutor_id": "ハンバーグ",
            "text": "まじーーー",
            "mention_to": []
        },
        {
            "utterance_id": 105,
            "interlocutor_id": "ハンバーグ",
            "text": "高っ",
            "mention_to": []
        }
    ],
    "evaluations": [
        {
            "interlocutor_id": "おにぎり",
            "informativeness": 5,
            "comprehension": 5,
            "familiarity": 5,
            "interest": 5,
            "proactiveness": 4,
            "satisfaction": 4
        },
        {
            "interlocutor_id": "ハンバーグ",
            "informativeness": 5,
            "comprehension": 5,
            "familiarity": 5,
            "interest": 5,
            "proactiveness": 5,
            "satisfaction": 5
        },
        {
            "interlocutor_id": "らっこ",
            "informativeness": 2,
            "comprehension": 3,
            "familiarity": 3,
            "interest": 2,
            "proactiveness": 3,
            "satisfaction": 2
        }
    ]
}