{
    "dialogue_id": "B14103",
    "dialogue_type": "Family",
    "interlocutors": [
        "くじら",
        "じゃがいも",
        "くま"
    ],
    "relationship": [
        "じゃがいも",
        "くま"
    ],
    "utterances": [
        {
            "utterance_id": 0,
            "interlocutor_id": "くじら",
            "text": "こんばんは",
            "mention_to": []
        },
        {
            "utterance_id": 1,
            "interlocutor_id": "じゃがいも",
            "text": "こんばんはです",
            "mention_to": []
        },
        {
            "utterance_id": 2,
            "interlocutor_id": "くま",
            "text": "こんばんわ",
            "mention_to": []
        },
        {
            "utterance_id": 3,
            "interlocutor_id": "くじら",
            "text": "趣味は何ですか？",
            "mention_to": []
        },
        {
            "utterance_id": 4,
            "interlocutor_id": "じゃがいも",
            "text": "趣味はかき氷食べ歩きです！",
            "mention_to": []
        },
        {
            "utterance_id": 5,
            "interlocutor_id": "じゃがいも",
            "text": "真冬でも食べてます！",
            "mention_to": []
        },
        {
            "utterance_id": 6,
            "interlocutor_id": "じゃがいも",
            "text": "寒いですけどね",
            "mention_to": []
        },
        {
            "utterance_id": 7,
            "interlocutor_id": "くま",
            "text": "@くじら この時期はスノボです",
            "mention_to": [
                "くじら"
            ]
        },
        {
            "utterance_id": 8,
            "interlocutor_id": "くじら",
            "text": "@じゃがいも かき氷好きなんですね",
            "mention_to": [
                "じゃがいも"
            ]
        },
        {
            "utterance_id": 9,
            "interlocutor_id": "じゃがいも",
            "text": "@くじら さぁどっちの話から行きましょう笑",
            "mention_to": [
                "くじら"
            ]
        },
        {
            "utterance_id": 10,
            "interlocutor_id": "じゃがいも",
            "text": "@くじら そうなんです！！",
            "mention_to": [
                "くじら"
            ]
        },
        {
            "utterance_id": 11,
            "interlocutor_id": "じゃがいも",
            "text": "今結構色々なお店あって",
            "mention_to": []
        },
        {
            "utterance_id": 12,
            "interlocutor_id": "くま",
            "text": "@くじら 私も付き合わされてます",
            "mention_to": [
                "くじら"
            ]
        },
        {
            "utterance_id": 13,
            "interlocutor_id": "じゃがいも",
            "text": "カボチャとかサツマイモとか",
            "mention_to": []
        },
        {
            "utterance_id": 14,
            "interlocutor_id": "じゃがいも",
            "text": "いろんな味があるんですよ〜",
            "mention_to": []
        },
        {
            "utterance_id": 15,
            "interlocutor_id": "じゃがいも",
            "text": "その分お高いですけどね",
            "mention_to": []
        },
        {
            "utterance_id": 16,
            "interlocutor_id": "くま",
            "text": "@じゃがいも 穀物系がおいしいね",
            "mention_to": [
                "じゃがいも"
            ]
        },
        {
            "utterance_id": 17,
            "interlocutor_id": "くじら",
            "text": "かぼちゃとかあるんですか！",
            "mention_to": []
        },
        {
            "utterance_id": 18,
            "interlocutor_id": "じゃがいも",
            "text": "かぼちゃは年がら年中あります",
            "mention_to": []
        },
        {
            "utterance_id": 19,
            "interlocutor_id": "じゃがいも",
            "text": "割と！",
            "mention_to": []
        },
        {
            "utterance_id": 20,
            "interlocutor_id": "くじら",
            "text": "お値段結構しますよね？",
            "mention_to": []
        },
        {
            "utterance_id": 21,
            "interlocutor_id": "じゃがいも",
            "text": "@くじら 季節にしかないのは栗ですね",
            "mention_to": [
                "くじら"
            ]
        },
        {
            "utterance_id": 22,
            "interlocutor_id": "くま",
            "text": "@くじら 最近はブルーハワイとかじゃないんですよね",
            "mention_to": [
                "くじら"
            ]
        },
        {
            "utterance_id": 23,
            "interlocutor_id": "じゃがいも",
            "text": "@くじら 最高額2400円です笑",
            "mention_to": [
                "くじら"
            ]
        },
        {
            "utterance_id": 24,
            "interlocutor_id": "くま",
            "text": "@じゃがいも さすがに高いな",
            "mention_to": [
                "じゃがいも"
            ]
        },
        {
            "utterance_id": 25,
            "interlocutor_id": "くじら",
            "text": "@じゃがいも 栗も美味しそうです",
            "mention_to": [
                "じゃがいも"
            ]
        },
        {
            "utterance_id": 26,
            "interlocutor_id": "くじら",
            "text": "ブルーハワイも食べてましたー",
            "mention_to": []
        },
        {
            "utterance_id": 27,
            "interlocutor_id": "くま",
            "text": "@くじら 秋は栗ばっかり食べてますね",
            "mention_to": [
                "くじら"
            ]
        },
        {
            "utterance_id": 28,
            "interlocutor_id": "くじら",
            "text": "今のはお洒落ですね",
            "mention_to": []
        },
        {
            "utterance_id": 29,
            "interlocutor_id": "じゃがいも",
            "text": "@くま まぁブルーハワイも好きなんですけどね",
            "mention_to": [
                "くま"
            ]
        },
        {
            "utterance_id": 30,
            "interlocutor_id": "くま",
            "text": "@くじら 小さいころは色んな味にわくわくしてましたね",
            "mention_to": [
                "くじら"
            ]
        },
        {
            "utterance_id": 31,
            "interlocutor_id": "くま",
            "text": "祭りとかのやつ",
            "mention_to": []
        },
        {
            "utterance_id": 32,
            "interlocutor_id": "くじら",
            "text": "@くま 私、栗が好きです",
            "mention_to": [
                "くま"
            ]
        },
        {
            "utterance_id": 33,
            "interlocutor_id": "くじら",
            "text": "モンブランが好きで",
            "mention_to": []
        },
        {
            "utterance_id": 34,
            "interlocutor_id": "じゃがいも",
            "text": "@くじら いいですね！",
            "mention_to": [
                "くじら"
            ]
        },
        {
            "utterance_id": 35,
            "interlocutor_id": "じゃがいも",
            "text": "うわ！",
            "mention_to": []
        },
        {
            "utterance_id": 36,
            "interlocutor_id": "じゃがいも",
            "text": "私もですよ〜！",
            "mention_to": []
        },
        {
            "utterance_id": 37,
            "interlocutor_id": "じゃがいも",
            "text": "モンブラン大好きです",
            "mention_to": []
        },
        {
            "utterance_id": 38,
            "interlocutor_id": "くじら",
            "text": "モンブランもお店調べて食べに行きますよー",
            "mention_to": []
        },
        {
            "utterance_id": 39,
            "interlocutor_id": "くま",
            "text": "@くじら であれば、いつか栗のかき氷も、、、",
            "mention_to": [
                "くじら"
            ]
        },
        {
            "utterance_id": 40,
            "interlocutor_id": "くま",
            "text": "@くじら いいですね",
            "mention_to": [
                "くじら"
            ]
        },
        {
            "utterance_id": 41,
            "interlocutor_id": "じゃがいも",
            "text": "@くじら 栗屋ってところいいですよ",
            "mention_to": [
                "くじら"
            ]
        },
        {
            "utterance_id": 42,
            "interlocutor_id": "じゃがいも",
            "text": "間違えた",
            "mention_to": []
        },
        {
            "utterance_id": 43,
            "interlocutor_id": "くじら",
            "text": "@くま 栗のかき氷食べたいです",
            "mention_to": [
                "くま"
            ]
        },
        {
            "utterance_id": 44,
            "interlocutor_id": "じゃがいも",
            "text": "和栗や",
            "mention_to": []
        },
        {
            "utterance_id": 45,
            "interlocutor_id": "くま",
            "text": "おすすめのモンブランありますか？",
            "mention_to": []
        },
        {
            "utterance_id": 46,
            "interlocutor_id": "くじら",
            "text": "@じゃがいも 和栗や知ってます。",
            "mention_to": [
                "じゃがいも"
            ]
        },
        {
            "utterance_id": 47,
            "interlocutor_id": "じゃがいも",
            "text": "@くじら 旦那がダロワイユのモンブラン推しです",
            "mention_to": [
                "くじら"
            ]
        },
        {
            "utterance_id": 48,
            "interlocutor_id": "じゃがいも",
            "text": "おっ！！！！",
            "mention_to": []
        },
        {
            "utterance_id": 49,
            "interlocutor_id": "くま",
            "text": "@くじら 来年の秋にぜひ",
            "mention_to": [
                "くじら"
            ]
        },
        {
            "utterance_id": 50,
            "interlocutor_id": "じゃがいも",
            "text": "和栗や知ってますか",
            "mention_to": []
        },
        {
            "utterance_id": 51,
            "interlocutor_id": "じゃがいも",
            "text": "美味しいですよね",
            "mention_to": []
        },
        {
            "utterance_id": 52,
            "interlocutor_id": "くじら",
            "text": "食べたくて1人で入りました",
            "mention_to": []
        },
        {
            "utterance_id": 53,
            "interlocutor_id": "じゃがいも",
            "text": "代々木公園とかにあったんじゃないかな",
            "mention_to": []
        },
        {
            "utterance_id": 54,
            "interlocutor_id": "じゃがいも",
            "text": "@くじら 素敵！",
            "mention_to": [
                "くじら"
            ]
        },
        {
            "utterance_id": 55,
            "interlocutor_id": "くじら",
            "text": "ちょっと待ちました",
            "mention_to": []
        },
        {
            "utterance_id": 56,
            "interlocutor_id": "くま",
            "text": "@じゃがいも ダロワイユは見た目が、、、",
            "mention_to": [
                "じゃがいも"
            ]
        },
        {
            "utterance_id": 57,
            "interlocutor_id": "じゃがいも",
            "text": "分かります",
            "mention_to": []
        },
        {
            "utterance_id": 58,
            "interlocutor_id": "じゃがいも",
            "text": "和栗やは待つ...",
            "mention_to": []
        },
        {
            "utterance_id": 59,
            "interlocutor_id": "くま",
            "text": "@くじら 待つんですね、、、",
            "mention_to": [
                "くじら"
            ]
        },
        {
            "utterance_id": 60,
            "interlocutor_id": "くま",
            "text": "人気店は大変だ",
            "mention_to": []
        },
        {
            "utterance_id": 61,
            "interlocutor_id": "くじら",
            "text": "ダロワイユも気になります",
            "mention_to": []
        },
        {
            "utterance_id": 62,
            "interlocutor_id": "じゃがいも",
            "text": "@くじら ダロワイユのモンブラン知ってます？",
            "mention_to": [
                "くじら"
            ]
        },
        {
            "utterance_id": 63,
            "interlocutor_id": "じゃがいも",
            "text": "写真で見る前に",
            "mention_to": []
        },
        {
            "utterance_id": 64,
            "interlocutor_id": "じゃがいも",
            "text": "まぁちょっとグロいです",
            "mention_to": []
        },
        {
            "utterance_id": 65,
            "interlocutor_id": "くま",
            "text": "@じゃがいも 閲覧は注意ですね",
            "mention_to": [
                "じゃがいも"
            ]
        },
        {
            "utterance_id": 66,
            "interlocutor_id": "くじら",
            "text": "@じゃがいも 他のお店のと違うんのですね",
            "mention_to": [
                "じゃがいも"
            ]
        },
        {
            "utterance_id": 67,
            "interlocutor_id": "じゃがいも",
            "text": "美味しいですけど、見た目なんでこれにしたの〜って気持ちになります",
            "mention_to": []
        },
        {
            "utterance_id": 68,
            "interlocutor_id": "じゃがいも",
            "text": "@くじら まぁ脳みそみたいなんですよ",
            "mention_to": [
                "くじら"
            ]
        },
        {
            "utterance_id": 69,
            "interlocutor_id": "くま",
            "text": "@くじら 見た目の癖がすごいです",
            "mention_to": [
                "くじら"
            ]
        },
        {
            "utterance_id": 70,
            "interlocutor_id": "くじら",
            "text": "それは気になります！",
            "mention_to": []
        },
        {
            "utterance_id": 71,
            "interlocutor_id": "じゃがいも",
            "text": "なんかふにゃふにゃした模様が",
            "mention_to": []
        },
        {
            "utterance_id": 72,
            "interlocutor_id": "くま",
            "text": "あとちょっとお高い",
            "mention_to": []
        },
        {
            "utterance_id": 73,
            "interlocutor_id": "くじら",
            "text": "インパクトがありますね",
            "mention_to": []
        },
        {
            "utterance_id": 74,
            "interlocutor_id": "じゃがいも",
            "text": "@くじら 美味しいらしいんですけど、私はどっにも見た目が嫌いで笑",
            "mention_to": [
                "くじら"
            ]
        },
        {
            "utterance_id": 75,
            "interlocutor_id": "くま",
            "text": "まあモンブランなら普通科",
            "mention_to": []
        },
        {
            "utterance_id": 76,
            "interlocutor_id": "じゃがいも",
            "text": "食べる気にならんのです",
            "mention_to": []
        },
        {
            "utterance_id": 77,
            "interlocutor_id": "くじら",
            "text": "モンブランも高いですよね",
            "mention_to": []
        },
        {
            "utterance_id": 78,
            "interlocutor_id": "じゃがいも",
            "text": "@くま ダロワイユは高いね",
            "mention_to": [
                "くま"
            ]
        },
        {
            "utterance_id": 79,
            "interlocutor_id": "くま",
            "text": "普通科になっちゃった",
            "mention_to": []
        },
        {
            "utterance_id": 80,
            "interlocutor_id": "じゃがいも",
            "text": "@くま じぶんに突っ込まないで",
            "mention_to": [
                "くま"
            ]
        },
        {
            "utterance_id": 81,
            "interlocutor_id": "じゃがいも",
            "text": "モンブラン高いですよ〜",
            "mention_to": []
        },
        {
            "utterance_id": 82,
            "interlocutor_id": "くま",
            "text": "@じゃがいも 相場はいくらくらいなんだろうか",
            "mention_to": [
                "じゃがいも"
            ]
        },
        {
            "utterance_id": 83,
            "interlocutor_id": "じゃがいも",
            "text": "多分下手したらかき氷と同じくらいしますよね",
            "mention_to": []
        },
        {
            "utterance_id": 84,
            "interlocutor_id": "くま",
            "text": "普通のケーキ屋だと５００円くらい？",
            "mention_to": []
        },
        {
            "utterance_id": 85,
            "interlocutor_id": "くじら",
            "text": "そうですよね。普通はいくらぐらいなんですかね？",
            "mention_to": []
        },
        {
            "utterance_id": 86,
            "interlocutor_id": "くま",
            "text": "@じゃがいも そこまでは行かんのでは？",
            "mention_to": [
                "じゃがいも"
            ]
        },
        {
            "utterance_id": 87,
            "interlocutor_id": "じゃがいも",
            "text": "@くま 多分コージーコーナーで500-600",
            "mention_to": [
                "くま"
            ]
        },
        {
            "utterance_id": 88,
            "interlocutor_id": "じゃがいも",
            "text": "@くま 高いやつは異様に高いわよ",
            "mention_to": [
                "くま"
            ]
        },
        {
            "utterance_id": 89,
            "interlocutor_id": "くま",
            "text": "ダロワイユは８００円くらいだった気がする",
            "mention_to": []
        },
        {
            "utterance_id": 90,
            "interlocutor_id": "くま",
            "text": "@じゃがいも 公休天下",
            "mention_to": [
                "じゃがいも"
            ]
        },
        {
            "utterance_id": 91,
            "interlocutor_id": "くじら",
            "text": "栗が高いですからね",
            "mention_to": []
        },
        {
            "utterance_id": 92,
            "interlocutor_id": "じゃがいも",
            "text": "@くま あ、思ったよりそんな感じなんだねなんか安心したかも",
            "mention_to": [
                "くま"
            ]
        },
        {
            "utterance_id": 93,
            "interlocutor_id": "じゃがいも",
            "text": "はい？",
            "mention_to": []
        },
        {
            "utterance_id": 94,
            "interlocutor_id": "じゃがいも",
            "text": "打ち間違いやめてください",
            "mention_to": []
        },
        {
            "utterance_id": 95,
            "interlocutor_id": "くま",
            "text": "@じゃがいも 予測変換やば",
            "mention_to": [
                "じゃがいも"
            ]
        },
        {
            "utterance_id": 96,
            "interlocutor_id": "くじら",
            "text": "毎年、栗をもらいますが",
            "mention_to": []
        },
        {
            "utterance_id": 97,
            "interlocutor_id": "じゃがいも",
            "text": "@くじら え、本当に羨ましい",
            "mention_to": [
                "くじら"
            ]
        },
        {
            "utterance_id": 98,
            "interlocutor_id": "くじら",
            "text": "剥くのがたいへんです",
            "mention_to": []
        },
        {
            "utterance_id": 99,
            "interlocutor_id": "じゃがいも",
            "text": "田舎からとかですか？",
            "mention_to": []
        },
        {
            "utterance_id": 100,
            "interlocutor_id": "くま",
            "text": "@くじら もらうんですね",
            "mention_to": [
                "くじら"
            ]
        },
        {
            "utterance_id": 101,
            "interlocutor_id": "じゃがいも",
            "text": "いやもうあの工数を考えれば絶対に栗系は高いんです",
            "mention_to": []
        },
        {
            "utterance_id": 102,
            "interlocutor_id": "くじら",
            "text": "そうですね。田舎からもらったりします",
            "mention_to": []
        }
    ],
    "evaluations": [
        {
            "interlocutor_id": "くじら",
            "informativeness": 4,
            "comprehension": 4,
            "familiarity": 4,
            "interest": 4,
            "proactiveness": 4,
            "satisfaction": 4
        },
        {
            "interlocutor_id": "じゃがいも",
            "informativeness": 4,
            "comprehension": 5,
            "familiarity": 4,
            "interest": 3,
            "proactiveness": 4,
            "satisfaction": 5
        },
        {
            "interlocutor_id": "くま",
            "informativeness": 4,
            "comprehension": 4,
            "familiarity": 3,
            "interest": 4,
            "proactiveness": 4,
            "satisfaction": 4
        }
    ]
}